setup.py
livedataframe/ExchangeInfo.py
livedataframe/LiveExchange.py
livedataframe/__init__.py
livedataframe.egg-info/PKG-INFO
livedataframe.egg-info/SOURCES.txt
livedataframe.egg-info/dependency_links.txt
livedataframe.egg-info/requires.txt
livedataframe.egg-info/top_level.txt